MANIFEST.in
README.rst
setup.py
tgext/__init__.py
tgext.matplotrender.egg-info/PKG-INFO
tgext.matplotrender.egg-info/SOURCES.txt
tgext.matplotrender.egg-info/dependency_links.txt
tgext.matplotrender.egg-info/entry_points.txt
tgext.matplotrender.egg-info/namespace_packages.txt
tgext.matplotrender.egg-info/not-zip-safe
tgext.matplotrender.egg-info/requires.txt
tgext.matplotrender.egg-info/top_level.txt
tgext/matplotrender/__init__.py
tgext/matplotrender/renderer.py