Metadata-Version: 1.0
Name: tgext.matplotrender
Version: 0.0.1
Summary: Renderer to expose matplotlib figures
Home-page: https://github.com/amol-/tgext.matplotrender
Author: Alessandro Molina
Author-email: amol@turbogears.org
License: MIT
Keywords: turbogears2.extension
Platform: UNKNOWN
